MANIFEST.in
README.md
setup.py
bin/shaku
shaku/__init__.py
shaku.egg-info/PKG-INFO
shaku.egg-info/SOURCES.txt
shaku.egg-info/dependency_links.txt
shaku.egg-info/requires.txt
shaku.egg-info/top_level.txt