Metadata-Version: 1.0
Name: shaku
Version: 0.0.3
Summary: Shaku 是一个脚本（命令等）定时执行的 WebService 框架，它提供了 RestAPI 来帮助开发人员更容易的将脚本设置成一个定时任务。
Home-page: https://pypi.python.org/pypi?:action=display&name=shaku
Author: xiaoh
Author-email: xiaoh@about.me
License: MIT Licence
Keywords: xiaoh,xingming,shaku,crontab,service
Platform: any
